LICENSE
README.md
setup.cfg
setup.py
mp/__init__.py
mp/conbase.py
mp/conserial.py
mp/conwebsock.py
mp/micropythonshell.py
mp/micropythonshell_up_listfiles.py
mp/mpfexp.py
mp/mpfshell.py
mp/pyboard.py
mp/pyboard_query.py
mp/retry.py
mp/term.py
mp/tokenizer.py
mp/util_serial.py
mp/util_serial_arg.py
mp/util_serial_list.py
mp/version.py
mp/firmware/__init__.py
mp/firmware/pybv11-20190125-v1.10.dfu
mp/firmware/pybv11-20210202-v1.14.dfu
mp/firmware/pydfu.py
mp/firmware/pydfu_orig.py
mp/firmware/update.py
mpfshell2.egg-info/PKG-INFO
mpfshell2.egg-info/SOURCES.txt
mpfshell2.egg-info/dependency_links.txt
mpfshell2.egg-info/entry_points.txt
mpfshell2.egg-info/requires.txt
mpfshell2.egg-info/top_level.txt